sync.v
module sync(
    input clk,rst, input [3:0] row, output reg s_row
);
reg a_row;

always @(negedge clk or posedge rst) begin
    if(rst)
    begin
      a_row <= 0;
      s_row <= 0;
    end    
    else begin
      a_row <= (row[0] || row[1] || row[2] || row[3]);
      s_row <= a_row;
    end
end

endmodule

row_sgnl.v
// All the coloumns are asserted

module row_sgnl(
    input [15:0]key, input [3:0] col, output reg [3:0] row
);

always @(key or col) begin
    row[0] = key[0] && col[0] || key[1] && col[1] || key[2] && col[2] || key[3] && col[3];
    row[1] = key[4] && col[0] || key[5] && col[1] || key[6] && col[2] || key[7] && col[3];
    row[2] = key[8] && col[0] || key[9] && col[1] || key[10] && col[2] || key[11] && col[3];
    row[3] = key[12] && col[0] || key[13] && col[1] || key[14] && col[2] || key[15] && col[3];
end

endmodule

hex_keypad.v
module hex_keypad(
    input [3:0]row, input s_row, clk, rst, output reg [3:0]code, col, output valid
);
parameter s_0 = 6'b000_001,
          s_1 = 6'b000_010,
          s_2 = 6'b000_100,
          s_3 = 6'b001_000,
          s_4 = 6'b010_000,
          s_5 = 6'b100_000;

reg [5:0] state, next_state;

assign valid = ((state == s_1) || (state == s_2) || (state == s_3) || (state == s_4)) && row;

always @(row or col) begin
    case({row,col}) 
        8'b0001_0001: code = 4'b0000;
        8'b0001_0010: code = 4'b0001;
        8'b0001_0100: code = 4'b0010;
        8'b0001_1000: code = 4'b0011;

        8'b0010_0001: code = 4'b0100;
        8'b0010_0010: code = 4'b0101;
        8'b0010_0100: code = 4'b0110;
        8'b0010_1000: code = 4'b0111;

        8'b0100_0001: code = 4'b1000;
        8'b0100_0010: code = 4'b1001;
        8'b0100_0100: code = 4'b1010;
        8'b0100_1000: code = 4'b1011;

        8'b1000_0001: code = 4'b1100;
        8'b1000_0010: code = 4'b1101;
        8'b1000_0100: code = 4'b1110;
        8'b1000_1000: code = 4'b1111;

        default : code  = 4'b0000;
    endcase
end

always @(posedge clk or posedge rst ) begin
    if (rst)
    state <= s_0;
    else
    next_state <= state;
end

always @(state or row or s_row) begin
    next_state = state;
    col = 4'b0000;
    case (state)
        s_0 : begin
                col = 4'b1111;
                if(s_row)
                next_state = s_1;
              end
        s_1 : begin
                col = 4'b0001;
                if(row)
                next_state = s_5;
                else
                next_state = s_2;
              end
        s_2 : begin
                col = 4'b0010;
                if(row)
                next_state = s_5;
                else
                next_state = s_3;
              end
        s_3 : begin
                col = 4'b0100;
                if(row)
                next_state = s_5;
                else
                next_state = s_4;
              end
        s_4 : begin
                col = 4'b1000;
                if(row)
                next_state = s_5;
                else
                next_state = s_0;
              end
        s_5 : begin
                col = 4'b1111;
                if(row == 4'b0000)
                next_state = s_0;
              end
    endcase    
end
endmodule

top.v
`include "hex_keypad.v"
`include "row_sgnl.v"
`include "sync.v"

module top(
    input clk, rst, input [15:0] key, output  valid, output [3:0] row, col, code
);
wire s_row;

hex_keypad M1(.row(row),  .s_row(s_row), .clk(clk), .rst(rst), .code(code), .col(col), .valid(valid));

row_sgnl M2(key, col,  row);

sync M3(clk, rst , row, s_row);

endmodule

tb.v
`timescale 1ns/1ps
module tb;
reg clk, rst;
reg [15:0] key;
wire  valid;
wire [3:0] row, col, code;

top DUT(clk, rst, key, valid, row, col, code);

integer i,j;
initial begin
  clk = 1'b0;
  forever #5 clk = ! clk;
end

initial begin
    $dumpfile("output.vcd");
    $dumpvars(0,tb);

    rst = 1'b1;
    #10;
    rst = 1'b0;

    for (i=0 ; i<=1; i=i+1) begin
        key = 0;
        #20;
      for(j = 0 ; j<=16; j=j+1) begin
        #20 key[j] = 1;
        #60;
        key = 0;

      end
    end
    $finish;
end
endmodule

output.vcd
$date
	Sat Dec 31 17:57:56 2022
$end
$version
	Icarus Verilog
$end
$timescale
	1ps
$end
$scope module tb $end
$var wire 1 ! valid $end
$var wire 4 " row [3:0] $end
$var wire 4 # col [3:0] $end
$var wire 4 $ code [3:0] $end
$var reg 1 % clk $end
$var reg 16 & key [15:0] $end
$var reg 1 ' rst $end
$var integer 32 ( i [31:0] $end
$var integer 32 ) j [31:0] $end
$scope module DUT $end
$var wire 1 % clk $end
$var wire 16 * key [15:0] $end
$var wire 1 ' rst $end
$var wire 1 ! valid $end
$var wire 1 + s_row $end
$var wire 4 , row [3:0] $end
$var wire 4 - col [3:0] $end
$var wire 4 . code [3:0] $end
$scope module M1 $end
$var wire 1 % clk $end
$var wire 1 ' rst $end
$var wire 1 ! valid $end
$var wire 1 + s_row $end
$var wire 4 / row [3:0] $end
$var parameter 6 0 s_0 $end
$var parameter 6 1 s_1 $end
$var parameter 6 2 s_2 $end
$var parameter 6 3 s_3 $end
$var parameter 6 4 s_4 $end
$var parameter 6 5 s_5 $end
$var reg 4 6 code [3:0] $end
$var reg 4 7 col [3:0] $end
$var reg 6 8 next_state [5:0] $end
$var reg 6 9 state [5:0] $end
$upscope $end
$scope module M2 $end
$var wire 4 : col [3:0] $end
$var wire 16 ; key [15:0] $end
$var reg 4 < row [3:0] $end
$upscope $end
$scope module M3 $end
$var wire 1 % clk $end
$var wire 4 = row [3:0] $end
$var wire 1 ' rst $end
$var reg 1 > a_row $end
$var reg 1 + s_row $end
$upscope $end
$upscope $end
$upscope $end
$enddefinitions $end
$comment Show the parameter values. $end
$dumpall
b100000 5
b10000 4
b1000 3
b100 2
b10 1
b1 0
$end
#0
$dumpvars
0>
bx =
bx <
bx ;
b1111 :
b1 9
b1 8
b1111 7
b0 6
bx /
b0 .
b1111 -
bx ,
0+
bx *
bx )
bx (
1'
bx &
0%
b0 $
b1111 #
bx "
0!
$end
#5000
1%
#10000
b1111 #
b1111 -
b1111 7
b1111 :
b0 "
b0 ,
b0 /
b0 <
b0 =
0%
b0 &
b0 *
b0 ;
b0 (
0'
#15000
1%
#20000
0%
#25000
1%
#30000
0%
b0 )
#35000
1%
#40000
0%
#45000
1%
#50000
1>
b1111 #
b1111 -
b1111 7
b1111 :
b1 "
b1 ,
b1 /
b1 <
b1 =
0%
b1 &
b1 *
b1 ;
#55000
1%
#60000
b10 8
b1111 #
b1111 -
b1111 7
b1111 :
1+
0%
#65000
1!
b100000 8
b1 #
b1 -
b1 7
b1 :
b10 9
1%
#70000
0%
#75000
0!
b1111 #
b1111 -
b1111 7
b1111 :
b100000 9
1%
#80000
0%
#85000
1%
#90000
0%
#95000
1%
#100000
0%
#105000
1%
#110000
0>
b1 8
b1111 #
b1111 -
b1111 7
b1111 :
b0 "
b0 ,
b0 /
b0 <
b0 =
0%
b1 )
b0 &
b0 *
b0 ;
#115000
b10 8
b1111 #
b1111 -
b1111 7
b1111 :
b1 9
1%
#120000
b1111 #
b1111 -
b1111 7
b1111 :
b1 8
0+
0%
#125000
1%
#130000
1>
b1111 #
b1111 -
b1111 7
b1111 :
b1 "
b1 ,
b1 /
b1 <
b1 =
0%
b10 &
b10 *
b10 ;
#135000
1%
#140000
b10 8
b1111 #
b1111 -
b1111 7
b1111 :
1+
0%
#145000
b0 "
b0 ,
b0 /
b0 <
b0 =
b100 8
b1 #
b1 -
b1 7
b1 :
b10 9
1%
#150000
0>
0%
#155000
1!
b1 $
b1 .
b1 6
b1 "
b1 ,
b1 /
b1 <
b1 =
b100000 8
b10 #
b10 -
b10 7
b10 :
b100 9
1%
#160000
b10 #
b10 -
b10 7
b10 :
b100000 8
0+
1>
0%
#165000
0!
b0 $
b0 .
b0 6
b1111 #
b1111 -
b1111 7
b1111 :
b100000 9
1%
#170000
b1111 #
b1111 -
b1111 7
b1111 :
1+
0%
#175000
1%
#180000
0%
#185000
1%
#190000
0>
b1 8
b1111 #
b1111 -
b1111 7
b1111 :
b0 "
b0 ,
b0 /
b0 <
b0 =
0%
b10 )
b0 &
b0 *
b0 ;
#195000
b10 8
b1111 #
b1111 -
b1111 7
b1111 :
b1 9
1%
#200000
b1111 #
b1111 -
b1111 7
b1111 :
b1 8
0+
0%
#205000
1%
#210000
1>
b1111 #
b1111 -
b1111 7
b1111 :
b1 "
b1 ,
b1 /
b1 <
b1 =
0%
b100 &
b100 *
b100 ;
#215000
1%
#220000
b10 8
b1111 #
b1111 -
b1111 7
b1111 :
1+
0%
#225000
b0 "
b0 ,
b0 /
b0 <
b0 =
b100 8
b1 #
b1 -
b1 7
b1 :
b10 9
1%
#230000
0>
0%
#235000
b1000 8
b10 #
b10 -
b10 7
b10 :
b100 9
1%
#240000
b10 #
b10 -
b10 7
b10 :
b1000 8
0+
0%
#245000
1!
b10 $
b10 .
b10 6
b1 "
b1 ,
b1 /
b1 <
b1 =
b100000 8
b100 #
b100 -
b100 7
b100 :
b1000 9
1%
#250000
1>
0%
#255000
0!
b0 $
b0 .
b0 6
b1111 #
b1111 -
b1111 7
b1111 :
b100000 9
1%
#260000
b1111 #
b1111 -
b1111 7
b1111 :
1+
0%
#265000
1%
#270000
0>
b1 8
b1111 #
b1111 -
b1111 7
b1111 :
b0 "
b0 ,
b0 /
b0 <
b0 =
0%
b11 )
b0 &
b0 *
b0 ;
#275000
b10 8
b1111 #
b1111 -
b1111 7
b1111 :
b1 9
1%
#280000
b1111 #
b1111 -
b1111 7
b1111 :
b1 8
0+
0%
#285000
1%
#290000
1>
b1111 #
b1111 -
b1111 7
b1111 :
b1 "
b1 ,
b1 /
b1 <
b1 =
0%
b1000 &
b1000 *
b1000 ;
#295000
1%
#300000
b10 8
b1111 #
b1111 -
b1111 7
b1111 :
1+
0%
#305000
b0 "
b0 ,
b0 /
b0 <
b0 =
b100 8
b1 #
b1 -
b1 7
b1 :
b10 9
1%
#310000
0>
0%
#315000
b1000 8
b10 #
b10 -
b10 7
b10 :
b100 9
1%
#320000
b10 #
b10 -
b10 7
b10 :
b1000 8
0+
0%
#325000
b10000 8
b100 #
b100 -
b100 7
b100 :
b1000 9
1%
#330000
0%
#335000
1!
b11 $
b11 .
b11 6
b1 "
b1 ,
b1 /
b1 <
b1 =
b100000 8
b1000 #
b1000 -
b1000 7
b1000 :
b10000 9
1%
#340000
1>
0%
#345000
b0 $
b0 .
b0 6
0!
b1111 #
b1111 -
b1111 7
b1111 :
b100000 9
1%
#350000
1+
0>
b1 8
b1111 #
b1111 -
b1111 7
b1111 :
b0 "
b0 ,
b0 /
b0 <
b0 =
0%
b100 )
b0 &
b0 *
b0 ;
#355000
b10 8
b1111 #
b1111 -
b1111 7
b1111 :
b1 9
1%
#360000
b1111 #
b1111 -
b1111 7
b1111 :
b1 8
0+
0%
#365000
1%
#370000
1>
b1111 #
b1111 -
b1111 7
b1111 :
b10 "
b10 ,
b10 /
b10 <
b10 =
0%
b10000 &
b10000 *
b10000 ;
#375000
1%
#380000
b10 8
b1111 #
b1111 -
b1111 7
b1111 :
1+
0%
#385000
1!
b100 $
b100 .
b100 6
b100000 8
b1 #
b1 -
b1 7
b1 :
b10 9
1%
#390000
0%
#395000
0!
b0 $
b0 .
b0 6
b1111 #
b1111 -
b1111 7
b1111 :
b100000 9
1%
#400000
0%
#405000
1%
#410000
0%
#415000
1%
#420000
0%
#425000
1%
#430000
0>
b1 8
b1111 #
b1111 -
b1111 7
b1111 :
b0 "
b0 ,
b0 /
b0 <
b0 =
0%
b101 )
b0 &
b0 *
b0 ;
#435000
b10 8
b1111 #
b1111 -
b1111 7
b1111 :
b1 9
1%
#440000
b1111 #
b1111 -
b1111 7
b1111 :
b1 8
0+
0%
#445000
1%
#450000
1>
b1111 #
b1111 -
b1111 7
b1111 :
b10 "
b10 ,
b10 /
b10 <
b10 =
0%
b100000 &
b100000 *
b100000 ;
#455000
1%
#460000
b10 8
b1111 #
b1111 -
b1111 7
b1111 :
1+
0%
#465000
b0 "
b0 ,
b0 /
b0 <
b0 =
b100 8
b1 #
b1 -
b1 7
b1 :
b10 9
1%
#470000
0>
0%
#475000
1!
b101 $
b101 .
b101 6
b10 "
b10 ,
b10 /
b10 <
b10 =
b100000 8
b10 #
b10 -
b10 7
b10 :
b100 9
1%
#480000
b10 #
b10 -
b10 7
b10 :
b100000 8
0+
1>
0%
#485000
0!
b0 $
b0 .
b0 6
b1111 #
b1111 -
b1111 7
b1111 :
b100000 9
1%
#490000
b1111 #
b1111 -
b1111 7
b1111 :
1+
0%
#495000
1%
#500000
0%
#505000
1%
#510000
0>
b1 8
b1111 #
b1111 -
b1111 7
b1111 :
b0 "
b0 ,
b0 /
b0 <
b0 =
0%
b110 )
b0 &
b0 *
b0 ;
#515000
b10 8
b1111 #
b1111 -
b1111 7
b1111 :
b1 9
1%
#520000
b1111 #
b1111 -
b1111 7
b1111 :
b1 8
0+
0%
#525000
1%
#530000
1>
b1111 #
b1111 -
b1111 7
b1111 :
b10 "
b10 ,
b10 /
b10 <
b10 =
0%
b1000000 &
b1000000 *
b1000000 ;
#535000
1%
#540000
b10 8
b1111 #
b1111 -
b1111 7
b1111 :
1+
0%
#545000
b0 "
b0 ,
b0 /
b0 <
b0 =
b100 8
b1 #
b1 -
b1 7
b1 :
b10 9
1%
#550000
0>
0%
#555000
b1000 8
b10 #
b10 -
b10 7
b10 :
b100 9
1%
#560000
b10 #
b10 -
b10 7
b10 :
b1000 8
0+
0%
#565000
1!
b110 $
b110 .
b110 6
b10 "
b10 ,
b10 /
b10 <
b10 =
b100000 8
b100 #
b100 -
b100 7
b100 :
b1000 9
1%
#570000
1>
0%
#575000
0!
b0 $
b0 .
b0 6
b1111 #
b1111 -
b1111 7
b1111 :
b100000 9
1%
#580000
b1111 #
b1111 -
b1111 7
b1111 :
1+
0%
#585000
1%
#590000
0>
b1 8
b1111 #
b1111 -
b1111 7
b1111 :
b0 "
b0 ,
b0 /
b0 <
b0 =
0%
b111 )
b0 &
b0 *
b0 ;
#595000
b10 8
b1111 #
b1111 -
b1111 7
b1111 :
b1 9
1%
#600000
b1111 #
b1111 -
b1111 7
b1111 :
b1 8
0+
0%
#605000
1%
#610000
1>
b1111 #
b1111 -
b1111 7
b1111 :
b10 "
b10 ,
b10 /
b10 <
b10 =
0%
b10000000 &
b10000000 *
b10000000 ;
#615000
1%
#620000
b10 8
b1111 #
b1111 -
b1111 7
b1111 :
1+
0%
#625000
b0 "
b0 ,
b0 /
b0 <
b0 =
b100 8
b1 #
b1 -
b1 7
b1 :
b10 9
1%
#630000
0>
0%
#635000
b1000 8
b10 #
b10 -
b10 7
b10 :
b100 9
1%
#640000
b10 #
b10 -
b10 7
b10 :
b1000 8
0+
0%
#645000
b10000 8
b100 #
b100 -
b100 7
b100 :
b1000 9
1%
#650000
0%
#655000
1!
b111 $
b111 .
b111 6
b10 "
b10 ,
b10 /
b10 <
b10 =
b100000 8
b1000 #
b1000 -
b1000 7
b1000 :
b10000 9
1%
#660000
1>
0%
#665000
b0 $
b0 .
b0 6
0!
b1111 #
b1111 -
b1111 7
b1111 :
b100000 9
1%
#670000
1+
0>
b1 8
b1111 #
b1111 -
b1111 7
b1111 :
b0 "
b0 ,
b0 /
b0 <
b0 =
0%
b1000 )
b0 &
b0 *
b0 ;
#675000
b10 8
b1111 #
b1111 -
b1111 7
b1111 :
b1 9
1%
#680000
b1111 #
b1111 -
b1111 7
b1111 :
b1 8
0+
0%
#685000
1%
#690000
1>
b1111 #
b1111 -
b1111 7
b1111 :
b100 "
b100 ,
b100 /
b100 <
b100 =
0%
b100000000 &
b100000000 *
b100000000 ;
#695000
1%
#700000
b10 8
b1111 #
b1111 -
b1111 7
b1111 :
1+
0%
#705000
1!
b1000 $
b1000 .
b1000 6
b100000 8
b1 #
b1 -
b1 7
b1 :
b10 9
1%
#710000
0%
#715000
0!
b0 $
b0 .
b0 6
b1111 #
b1111 -
b1111 7
b1111 :
b100000 9
1%
#720000
0%
#725000
1%
#730000
0%
#735000
1%
#740000
0%
#745000
1%
#750000
0>
b1 8
b1111 #
b1111 -
b1111 7
b1111 :
b0 "
b0 ,
b0 /
b0 <
b0 =
0%
b1001 )
b0 &
b0 *
b0 ;
#755000
b10 8
b1111 #
b1111 -
b1111 7
b1111 :
b1 9
1%
#760000
b1111 #
b1111 -
b1111 7
b1111 :
b1 8
0+
0%
#765000
1%
#770000
1>
b1111 #
b1111 -
b1111 7
b1111 :
b100 "
b100 ,
b100 /
b100 <
b100 =
0%
b1000000000 &
b1000000000 *
b1000000000 ;
#775000
1%
#780000
b10 8
b1111 #
b1111 -
b1111 7
b1111 :
1+
0%
#785000
b0 "
b0 ,
b0 /
b0 <
b0 =
b100 8
b1 #
b1 -
b1 7
b1 :
b10 9
1%
#790000
0>
0%
#795000
1!
b1001 $
b1001 .
b1001 6
b100 "
b100 ,
b100 /
b100 <
b100 =
b100000 8
b10 #
b10 -
b10 7
b10 :
b100 9
1%
#800000
b10 #
b10 -
b10 7
b10 :
b100000 8
0+
1>
0%
#805000
0!
b0 $
b0 .
b0 6
b1111 #
b1111 -
b1111 7
b1111 :
b100000 9
1%
#810000
b1111 #
b1111 -
b1111 7
b1111 :
1+
0%
#815000
1%
#820000
0%
#825000
1%
#830000
0>
b1 8
b1111 #
b1111 -
b1111 7
b1111 :
b0 "
b0 ,
b0 /
b0 <
b0 =
0%
b1010 )
b0 &
b0 *
b0 ;
#835000
b10 8
b1111 #
b1111 -
b1111 7
b1111 :
b1 9
1%
#840000
b1111 #
b1111 -
b1111 7
b1111 :
b1 8
0+
0%
#845000
1%
#850000
1>
b1111 #
b1111 -
b1111 7
b1111 :
b100 "
b100 ,
b100 /
b100 <
b100 =
0%
b10000000000 &
b10000000000 *
b10000000000 ;
#855000
1%
#860000
b10 8
b1111 #
b1111 -
b1111 7
b1111 :
1+
0%
#865000
b0 "
b0 ,
b0 /
b0 <
b0 =
b100 8
b1 #
b1 -
b1 7
b1 :
b10 9
1%
#870000
0>
0%
#875000
b1000 8
b10 #
b10 -
b10 7
b10 :
b100 9
1%
#880000
b10 #
b10 -
b10 7
b10 :
b1000 8
0+
0%
#885000
1!
b1010 $
b1010 .
b1010 6
b100 "
b100 ,
b100 /
b100 <
b100 =
b100000 8
b100 #
b100 -
b100 7
b100 :
b1000 9
1%
#890000
1>
0%
#895000
0!
b0 $
b0 .
b0 6
b1111 #
b1111 -
b1111 7
b1111 :
b100000 9
1%
#900000
b1111 #
b1111 -
b1111 7
b1111 :
1+
0%
#905000
1%
#910000
0>
b1 8
b1111 #
b1111 -
b1111 7
b1111 :
b0 "
b0 ,
b0 /
b0 <
b0 =
0%
b1011 )
b0 &
b0 *
b0 ;
#915000
b10 8
b1111 #
b1111 -
b1111 7
b1111 :
b1 9
1%
#920000
b1111 #
b1111 -
b1111 7
b1111 :
b1 8
0+
0%
#925000
1%
#930000
1>
b1111 #
b1111 -
b1111 7
b1111 :
b100 "
b100 ,
b100 /
b100 <
b100 =
0%
b100000000000 &
b100000000000 *
b100000000000 ;
#935000
1%
#940000
b10 8
b1111 #
b1111 -
b1111 7
b1111 :
1+
0%
#945000
b0 "
b0 ,
b0 /
b0 <
b0 =
b100 8
b1 #
b1 -
b1 7
b1 :
b10 9
1%
#950000
0>
0%
#955000
b1000 8
b10 #
b10 -
b10 7
b10 :
b100 9
1%
#960000
b10 #
b10 -
b10 7
b10 :
b1000 8
0+
0%
#965000
b10000 8
b100 #
b100 -
b100 7
b100 :
b1000 9
1%
#970000
0%
#975000
1!
b1011 $
b1011 .
b1011 6
b100 "
b100 ,
b100 /
b100 <
b100 =
b100000 8
b1000 #
b1000 -
b1000 7
b1000 :
b10000 9
1%
#980000
1>
0%
#985000
b0 $
b0 .
b0 6
0!
b1111 #
b1111 -
b1111 7
b1111 :
b100000 9
1%
#990000
1+
0>
b1 8
b1111 #
b1111 -
b1111 7
b1111 :
b0 "
b0 ,
b0 /
b0 <
b0 =
0%
b1100 )
b0 &
b0 *
b0 ;
#995000
b10 8
b1111 #
b1111 -
b1111 7
b1111 :
b1 9
1%
#1000000
b1111 #
b1111 -
b1111 7
b1111 :
b1 8
0+
0%
#1005000
1%
#1010000
1>
b1111 #
b1111 -
b1111 7
b1111 :
b1000 "
b1000 ,
b1000 /
b1000 <
b1000 =
0%
b1000000000000 &
b1000000000000 *
b1000000000000 ;
#1015000
1%
#1020000
b10 8
b1111 #
b1111 -
b1111 7
b1111 :
1+
0%
#1025000
1!
b1100 $
b1100 .
b1100 6
b100000 8
b1 #
b1 -
b1 7
b1 :
b10 9
1%
#1030000
0%
#1035000
0!
b0 $
b0 .
b0 6
b1111 #
b1111 -
b1111 7
b1111 :
b100000 9
1%
#1040000
0%
#1045000
1%
#1050000
0%
#1055000
1%
#1060000
0%
#1065000
1%
#1070000
0>
b1 8
b1111 #
b1111 -
b1111 7
b1111 :
b0 "
b0 ,
b0 /
b0 <
b0 =
0%
b1101 )
b0 &
b0 *
b0 ;
#1075000
b10 8
b1111 #
b1111 -
b1111 7
b1111 :
b1 9
1%
#1080000
b1111 #
b1111 -
b1111 7
b1111 :
b1 8
0+
0%
#1085000
1%
#1090000
1>
b1111 #
b1111 -
b1111 7
b1111 :
b1000 "
b1000 ,
b1000 /
b1000 <
b1000 =
0%
b10000000000000 &
b10000000000000 *
b10000000000000 ;
#1095000
1%
#1100000
b10 8
b1111 #
b1111 -
b1111 7
b1111 :
1+
0%
#1105000
b0 "
b0 ,
b0 /
b0 <
b0 =
b100 8
b1 #
b1 -
b1 7
b1 :
b10 9
1%
#1110000
0>
0%
#1115000
1!
b1101 $
b1101 .
b1101 6
b1000 "
b1000 ,
b1000 /
b1000 <
b1000 =
b100000 8
b10 #
b10 -
b10 7
b10 :
b100 9
1%
#1120000
b10 #
b10 -
b10 7
b10 :
b100000 8
0+
1>
0%
#1125000
0!
b0 $
b0 .
b0 6
b1111 #
b1111 -
b1111 7
b1111 :
b100000 9
1%
#1130000
b1111 #
b1111 -
b1111 7
b1111 :
1+
0%
#1135000
1%
#1140000
0%
#1145000
1%
#1150000
0>
b1 8
b1111 #
b1111 -
b1111 7
b1111 :
b0 "
b0 ,
b0 /
b0 <
b0 =
0%
b1110 )
b0 &
b0 *
b0 ;
#1155000
b10 8
b1111 #
b1111 -
b1111 7
b1111 :
b1 9
1%
#1160000
b1111 #
b1111 -
b1111 7
b1111 :
b1 8
0+
0%
#1165000
1%
#1170000
1>
b1111 #
b1111 -
b1111 7
b1111 :
b1000 "
b1000 ,
b1000 /
b1000 <
b1000 =
0%
b100000000000000 &
b100000000000000 *
b100000000000000 ;
#1175000
1%
#1180000
b10 8
b1111 #
b1111 -
b1111 7
b1111 :
1+
0%
#1185000
b0 "
b0 ,
b0 /
b0 <
b0 =
b100 8
b1 #
b1 -
b1 7
b1 :
b10 9
1%
#1190000
0>
0%
#1195000
b1000 8
b10 #
b10 -
b10 7
b10 :
b100 9
1%
#1200000
b10 #
b10 -
b10 7
b10 :
b1000 8
0+
0%
#1205000
1!
b1110 $
b1110 .
b1110 6
b1000 "
b1000 ,
b1000 /
b1000 <
b1000 =
b100000 8
b100 #
b100 -
b100 7
b100 :
b1000 9
1%
#1210000
1>
0%
#1215000
0!
b0 $
b0 .
b0 6
b1111 #
b1111 -
b1111 7
b1111 :
b100000 9
1%
#1220000
b1111 #
b1111 -
b1111 7
b1111 :
1+
0%
#1225000
1%
#1230000
0>
b1 8
b1111 #
b1111 -
b1111 7
b1111 :
b0 "
b0 ,
b0 /
b0 <
b0 =
0%
b1111 )
b0 &
b0 *
b0 ;
#1235000
b10 8
b1111 #
b1111 -
b1111 7
b1111 :
b1 9
1%
#1240000
b1111 #
b1111 -
b1111 7
b1111 :
b1 8
0+
0%
#1245000
1%
#1250000
1>
b1111 #
b1111 -
b1111 7
b1111 :
b1000 "
b1000 ,
b1000 /
b1000 <
b1000 =
0%
b1000000000000000 &
b1000000000000000 *
b1000000000000000 ;
#1255000
1%
#1260000
b10 8
b1111 #
b1111 -
b1111 7
b1111 :
1+
0%
#1265000
b0 "
b0 ,
b0 /
b0 <
b0 =
b100 8
b1 #
b1 -
b1 7
b1 :
b10 9
1%
#1270000
0>
0%
#1275000
b1000 8
b10 #
b10 -
b10 7
b10 :
b100 9
1%
#1280000
b10 #
b10 -
b10 7
b10 :
b1000 8
0+
0%
#1285000
b10000 8
b100 #
b100 -
b100 7
b100 :
b1000 9
1%
#1290000
0%
#1295000
1!
b1111 $
b1111 .
b1111 6
b1000 "
b1000 ,
b1000 /
b1000 <
b1000 =
b100000 8
b1000 #
b1000 -
b1000 7
b1000 :
b10000 9
1%
#1300000
1>
0%
#1305000
b0 $
b0 .
b0 6
0!
b1111 #
b1111 -
b1111 7
b1111 :
b100000 9
1%
#1310000
1+
0>
b1 8
b1111 #
b1111 -
b1111 7
b1111 :
b0 "
b0 ,
b0 /
b0 <
b0 =
0%
b10000 )
b0 &
b0 *
b0 ;
#1315000
b10 8
b1111 #
b1111 -
b1111 7
b1111 :
b1 9
1%
#1320000
b1111 #
b1111 -
b1111 7
b1111 :
b1 8
0+
0%
#1325000
1%
#1330000
0%
#1335000
1%
#1340000
0%
#1345000
1%
#1350000
0%
#1355000
1%
#1360000
0%
#1365000
1%
#1370000
0%
#1375000
1%
#1380000
0%
#1385000
1%
#1390000
0%
b1 (
b10001 )
#1395000
1%
#1400000
0%
#1405000
1%
#1410000
0%
b0 )
#1415000
1%
#1420000
0%
#1425000
1%
#1430000
1>
b1111 #
b1111 -
b1111 7
b1111 :
b1 "
b1 ,
b1 /
b1 <
b1 =
0%
b1 &
b1 *
b1 ;
#1435000
1%
#1440000
b10 8
b1111 #
b1111 -
b1111 7
b1111 :
1+
0%
#1445000
1!
b100000 8
b1 #
b1 -
b1 7
b1 :
b10 9
1%
#1450000
0%
#1455000
0!
b1111 #
b1111 -
b1111 7
b1111 :
b100000 9
1%
#1460000
0%
#1465000
1%
#1470000
0%
#1475000
1%
#1480000
0%
#1485000
1%
#1490000
0>
b1 8
b1111 #
b1111 -
b1111 7
b1111 :
b0 "
b0 ,
b0 /
b0 <
b0 =
0%
b1 )
b0 &
b0 *
b0 ;
#1495000
b10 8
b1111 #
b1111 -
b1111 7
b1111 :
b1 9
1%
#1500000
b1111 #
b1111 -
b1111 7
b1111 :
b1 8
0+
0%
#1505000
1%
#1510000
1>
b1111 #
b1111 -
b1111 7
b1111 :
b1 "
b1 ,
b1 /
b1 <
b1 =
0%
b10 &
b10 *
b10 ;
#1515000
1%
#1520000
b10 8
b1111 #
b1111 -
b1111 7
b1111 :
1+
0%
#1525000
b0 "
b0 ,
b0 /
b0 <
b0 =
b100 8
b1 #
b1 -
b1 7
b1 :
b10 9
1%
#1530000
0>
0%
#1535000
1!
b1 $
b1 .
b1 6
b1 "
b1 ,
b1 /
b1 <
b1 =
b100000 8
b10 #
b10 -
b10 7
b10 :
b100 9
1%
#1540000
b10 #
b10 -
b10 7
b10 :
b100000 8
0+
1>
0%
#1545000
0!
b0 $
b0 .
b0 6
b1111 #
b1111 -
b1111 7
b1111 :
b100000 9
1%
#1550000
b1111 #
b1111 -
b1111 7
b1111 :
1+
0%
#1555000
1%
#1560000
0%
#1565000
1%
#1570000
0>
b1 8
b1111 #
b1111 -
b1111 7
b1111 :
b0 "
b0 ,
b0 /
b0 <
b0 =
0%
b10 )
b0 &
b0 *
b0 ;
#1575000
b10 8
b1111 #
b1111 -
b1111 7
b1111 :
b1 9
1%
#1580000
b1111 #
b1111 -
b1111 7
b1111 :
b1 8
0+
0%
#1585000
1%
#1590000
1>
b1111 #
b1111 -
b1111 7
b1111 :
b1 "
b1 ,
b1 /
b1 <
b1 =
0%
b100 &
b100 *
b100 ;
#1595000
1%
#1600000
b10 8
b1111 #
b1111 -
b1111 7
b1111 :
1+
0%
#1605000
b0 "
b0 ,
b0 /
b0 <
b0 =
b100 8
b1 #
b1 -
b1 7
b1 :
b10 9
1%
#1610000
0>
0%
#1615000
b1000 8
b10 #
b10 -
b10 7
b10 :
b100 9
1%
#1620000
b10 #
b10 -
b10 7
b10 :
b1000 8
0+
0%
#1625000
1!
b10 $
b10 .
b10 6
b1 "
b1 ,
b1 /
b1 <
b1 =
b100000 8
b100 #
b100 -
b100 7
b100 :
b1000 9
1%
#1630000
1>
0%
#1635000
0!
b0 $
b0 .
b0 6
b1111 #
b1111 -
b1111 7
b1111 :
b100000 9
1%
#1640000
b1111 #
b1111 -
b1111 7
b1111 :
1+
0%
#1645000
1%
#1650000
0>
b1 8
b1111 #
b1111 -
b1111 7
b1111 :
b0 "
b0 ,
b0 /
b0 <
b0 =
0%
b11 )
b0 &
b0 *
b0 ;
#1655000
b10 8
b1111 #
b1111 -
b1111 7
b1111 :
b1 9
1%
#1660000
b1111 #
b1111 -
b1111 7
b1111 :
b1 8
0+
0%
#1665000
1%
#1670000
1>
b1111 #
b1111 -
b1111 7
b1111 :
b1 "
b1 ,
b1 /
b1 <
b1 =
0%
b1000 &
b1000 *
b1000 ;
#1675000
1%
#1680000
b10 8
b1111 #
b1111 -
b1111 7
b1111 :
1+
0%
#1685000
b0 "
b0 ,
b0 /
b0 <
b0 =
b100 8
b1 #
b1 -
b1 7
b1 :
b10 9
1%
#1690000
0>
0%
#1695000
b1000 8
b10 #
b10 -
b10 7
b10 :
b100 9
1%
#1700000
b10 #
b10 -
b10 7
b10 :
b1000 8
0+
0%
#1705000
b10000 8
b100 #
b100 -
b100 7
b100 :
b1000 9
1%
#1710000
0%
#1715000
1!
b11 $
b11 .
b11 6
b1 "
b1 ,
b1 /
b1 <
b1 =
b100000 8
b1000 #
b1000 -
b1000 7
b1000 :
b10000 9
1%
#1720000
1>
0%
#1725000
b0 $
b0 .
b0 6
0!
b1111 #
b1111 -
b1111 7
b1111 :
b100000 9
1%
#1730000
1+
0>
b1 8
b1111 #
b1111 -
b1111 7
b1111 :
b0 "
b0 ,
b0 /
b0 <
b0 =
0%
b100 )
b0 &
b0 *
b0 ;
#1735000
b10 8
b1111 #
b1111 -
b1111 7
b1111 :
b1 9
1%
